
	   {
			"title": "French Quarter Fest Poster",
			"link": "https://www.flickr.com/photos/139350096@N08/25137523473/",
			"media": {"m":"https://farm2.staticflickr.com/1671/25137523473_3092b019d1_m.jpg"},
			"date_taken": "2014-07-14T16:44:44-08:00",
			"description": " <p><a href=\"https://www.flickr.com/people/139350096@N08/\">myheirloomm<\/a> posted a photo:<\/p> <p><a href=\"https://www.flickr.com/photos/139350096@N08/25137523473/\" title=\"French Quarter Fest Poster\"><img src=\"https://farm2.staticflickr.com/1671/25137523473_3092b019d1_m.jpg\" width=\"240\" height=\"180\" alt=\"French Quarter Fest Poster\" /><\/a><\/p> ",
			"published": "2016-03-13T20:04:11Z",
			"author": "nobody@flickr.com (myheirloomm)",
			"author_id": "139350096@N08",
			"tags": ""
	   },
	   {
			"title": "photo 5",
			"link": "https://www.flickr.com/photos/139350096@N08/25668971431/",
			"media": {"m":"https://farm2.staticflickr.com/1672/25668971431_c35ac179fc_m.jpg"},
			"date_taken": "2014-02-08T13:23:20-08:00",
			"description": " <p><a href=\"https://www.flickr.com/people/139350096@N08/\">myheirloomm<\/a> posted a photo:<\/p> <p><a href=\"https://www.flickr.com/photos/139350096@N08/25668971431/\" title=\"photo 5\"><img src=\"https://farm2.staticflickr.com/1672/25668971431_c35ac179fc_m.jpg\" width=\"180\" height=\"240\" alt=\"photo 5\" /><\/a><\/p> ",
			"published": "2016-03-13T20:01:27Z",
			"author": "nobody@flickr.com (myheirloomm)",
			"author_id": "139350096@N08",
			"tags": ""
	   },
	   {
			"title": "photo 5 (5)",
			"link": "https://www.flickr.com/photos/139350096@N08/25764045255/",
			"media": {"m":"https://farm2.staticflickr.com/1479/25764045255_d865455053_m.jpg"},
			"date_taken": "2014-02-08T13:52:42-08:00",
			"description": " <p><a href=\"https://www.flickr.com/people/139350096@N08/\">myheirloomm<\/a> posted a photo:<\/p> <p><a href=\"https://www.flickr.com/photos/139350096@N08/25764045255/\" title=\"photo 5 (5)\"><img src=\"https://farm2.staticflickr.com/1479/25764045255_d865455053_m.jpg\" width=\"240\" height=\"180\" alt=\"photo 5 (5)\" /><\/a><\/p> ",
			"published": "2016-03-13T20:01:26Z",
			"author": "nobody@flickr.com (myheirloomm)",
			"author_id": "139350096@N08",
			"tags": ""
	   },
	   {
			"title": "photo 5 (4)",
			"link": "https://www.flickr.com/photos/139350096@N08/25133605424/",
			"media": {"m":"https://farm2.staticflickr.com/1663/25133605424_02680aabf2_m.jpg"},
			"date_taken": "2014-02-08T13:49:04-08:00",
			"description": " <p><a href=\"https://www.flickr.com/people/139350096@N08/\">myheirloomm<\/a> posted a photo:<\/p> <p><a href=\"https://www.flickr.com/photos/139350096@N08/25133605424/\" title=\"photo 5 (4)\"><img src=\"https://farm2.staticflickr.com/1663/25133605424_02680aabf2_m.jpg\" width=\"180\" height=\"240\" alt=\"photo 5 (4)\" /><\/a><\/p> ",
			"published": "2016-03-13T20:01:23Z",
			"author": "nobody@flickr.com (myheirloomm)",
			"author_id": "139350096@N08",
			"tags": ""
	   },
	   {
			"title": "photo 5 (3)",
			"link": "https://www.flickr.com/photos/139350096@N08/25643089472/",
			"media": {"m":"https://farm2.staticflickr.com/1530/25643089472_bbc8ff9216_m.jpg"},
			"date_taken": "2014-02-08T13:46:17-08:00",
			"description": " <p><a href=\"https://www.flickr.com/people/139350096@N08/\">myheirloomm<\/a> posted a photo:<\/p> <p><a href=\"https://www.flickr.com/photos/139350096@N08/25643089472/\" title=\"photo 5 (3)\"><img src=\"https://farm2.staticflickr.com/1530/25643089472_bbc8ff9216_m.jpg\" width=\"180\" height=\"240\" alt=\"photo 5 (3)\" /><\/a><\/p> ",
			"published": "2016-03-13T20:01:21Z",
			"author": "nobody@flickr.com (myheirloomm)",
			"author_id": "139350096@N08",
			"tags": ""
	   },
	   {
			"title": "photo 5 (2)",
			"link": "https://www.flickr.com/photos/139350096@N08/25137452913/",
			"media": {"m":"https://farm2.staticflickr.com/1627/25137452913_62650b7469_m.jpg"},
			"date_taken": "2014-02-08T13:40:52-08:00",
			"description": " <p><a href=\"https://www.flickr.com/people/139350096@N08/\">myheirloomm<\/a> posted a photo:<\/p> <p><a href=\"https://www.flickr.com/photos/139350096@N08/25137452913/\" title=\"photo 5 (2)\"><img src=\"https://farm2.staticflickr.com/1627/25137452913_62650b7469_m.jpg\" width=\"240\" height=\"180\" alt=\"photo 5 (2)\" /><\/a><\/p> ",
			"published": "2016-03-13T20:01:18Z",
			"author": "nobody@flickr.com (myheirloomm)",
			"author_id": "139350096@N08",
			"tags": ""
	   },
	   {
			"title": "photo 4",
			"link": "https://www.flickr.com/photos/139350096@N08/25137451523/",
			"media": {"m":"https://farm2.staticflickr.com/1707/25137451523_26d8c0df6c_m.jpg"},
			"date_taken": "2014-02-08T13:23:04-08:00",
			"description": " <p><a href=\"https://www.flickr.com/people/139350096@N08/\">myheirloomm<\/a> posted a photo:<\/p> <p><a href=\"https://www.flickr.com/photos/139350096@N08/25137451523/\" title=\"photo 4\"><img src=\"https://farm2.staticflickr.com/1707/25137451523_26d8c0df6c_m.jpg\" width=\"180\" height=\"240\" alt=\"photo 4\" /><\/a><\/p> ",
			"published": "2016-03-13T20:01:15Z",
			"author": "nobody@flickr.com (myheirloomm)",
			"author_id": "139350096@N08",
			"tags": ""
	   },
	   {
			"title": "photo 4 (5)",
			"link": "https://www.flickr.com/photos/139350096@N08/25668965971/",
			"media": {"m":"https://farm2.staticflickr.com/1473/25668965971_880aa50377_m.jpg"},
			"date_taken": "2014-02-08T13:52:18-08:00",
			"description": " <p><a href=\"https://www.flickr.com/people/139350096@N08/\">myheirloomm<\/a> posted a photo:<\/p> <p><a href=\"https://www.flickr.com/photos/139350096@N08/25668965971/\" title=\"photo 4 (5)\"><img src=\"https://farm2.staticflickr.com/1473/25668965971_880aa50377_m.jpg\" width=\"240\" height=\"180\" alt=\"photo 4 (5)\" /><\/a><\/p> ",
			"published": "2016-03-13T20:01:14Z",
			"author": "nobody@flickr.com (myheirloomm)",
			"author_id": "139350096@N08",
			"tags": ""
	   },
	   {
			"title": "photo 4 (4)",
			"link": "https://www.flickr.com/photos/139350096@N08/25643085252/",
			"media": {"m":"https://farm2.staticflickr.com/1475/25643085252_1191d505df_m.jpg"},
			"date_taken": "2014-02-08T13:48:19-08:00",
			"description": " <p><a href=\"https://www.flickr.com/people/139350096@N08/\">myheirloomm<\/a> posted a photo:<\/p> <p><a href=\"https://www.flickr.com/photos/139350096@N08/25643085252/\" title=\"photo 4 (4)\"><img src=\"https://farm2.staticflickr.com/1475/25643085252_1191d505df_m.jpg\" width=\"180\" height=\"240\" alt=\"photo 4 (4)\" /><\/a><\/p> ",
			"published": "2016-03-13T20:01:11Z",
			"author": "nobody@flickr.com (myheirloomm)",
			"author_id": "139350096@N08",
			"tags": ""
	   },
	   {
			"title": "photo 4 (3)",
			"link": "https://www.flickr.com/photos/139350096@N08/25137449063/",
			"media": {"m":"https://farm2.staticflickr.com/1719/25137449063_7229c8f062_m.jpg"},
			"date_taken": "2014-02-08T13:46:02-08:00",
			"description": " <p><a href=\"https://www.flickr.com/people/139350096@N08/\">myheirloomm<\/a> posted a photo:<\/p> <p><a href=\"https://www.flickr.com/photos/139350096@N08/25137449063/\" title=\"photo 4 (3)\"><img src=\"https://farm2.staticflickr.com/1719/25137449063_7229c8f062_m.jpg\" width=\"180\" height=\"240\" alt=\"photo 4 (3)\" /><\/a><\/p> ",
			"published": "2016-03-13T20:01:09Z",
			"author": "nobody@flickr.com (myheirloomm)",
			"author_id": "139350096@N08",
			"tags": ""
	   },
	   {
			"title": "photo 4 (2)",
			"link": "https://www.flickr.com/photos/139350096@N08/25643083542/",
			"media": {"m":"https://farm2.staticflickr.com/1703/25643083542_eeddb9b3a4_m.jpg"},
			"date_taken": "2014-02-08T13:40:45-08:00",
			"description": " <p><a href=\"https://www.flickr.com/people/139350096@N08/\">myheirloomm<\/a> posted a photo:<\/p> <p><a href=\"https://www.flickr.com/photos/139350096@N08/25643083542/\" title=\"photo 4 (2)\"><img src=\"https://farm2.staticflickr.com/1703/25643083542_eeddb9b3a4_m.jpg\" width=\"240\" height=\"180\" alt=\"photo 4 (2)\" /><\/a><\/p> ",
			"published": "2016-03-13T20:01:07Z",
			"author": "nobody@flickr.com (myheirloomm)",
			"author_id": "139350096@N08",
			"tags": ""
	   },
	   {
			"title": "photo 4 (1)",
			"link": "https://www.flickr.com/photos/139350096@N08/25133598154/",
			"media": {"m":"https://farm2.staticflickr.com/1476/25133598154_b8a9c8b0b0_m.jpg"},
			"date_taken": "2014-02-08T13:24:14-08:00",
			"description": " <p><a href=\"https://www.flickr.com/people/139350096@N08/\">myheirloomm<\/a> posted a photo:<\/p> <p><a href=\"https://www.flickr.com/photos/139350096@N08/25133598154/\" title=\"photo 4 (1)\"><img src=\"https://farm2.staticflickr.com/1476/25133598154_b8a9c8b0b0_m.jpg\" width=\"180\" height=\"240\" alt=\"photo 4 (1)\" /><\/a><\/p> ",
			"published": "2016-03-13T20:01:05Z",
			"author": "nobody@flickr.com (myheirloomm)",
			"author_id": "139350096@N08",
			"tags": ""
	   },
	   {
			"title": "photo 3",
			"link": "https://www.flickr.com/photos/139350096@N08/25668961761/",
			"media": {"m":"https://farm2.staticflickr.com/1716/25668961761_5a395b2567_m.jpg"},
			"date_taken": "2014-02-08T13:21:37-08:00",
			"description": " <p><a href=\"https://www.flickr.com/people/139350096@N08/\">myheirloomm<\/a> posted a photo:<\/p> <p><a href=\"https://www.flickr.com/photos/139350096@N08/25668961761/\" title=\"photo 3\"><img src=\"https://farm2.staticflickr.com/1716/25668961761_5a395b2567_m.jpg\" width=\"180\" height=\"240\" alt=\"photo 3\" /><\/a><\/p> ",
			"published": "2016-03-13T20:01:04Z",
			"author": "nobody@flickr.com (myheirloomm)",
			"author_id": "139350096@N08",
			"tags": ""
	   },
	   {
			"title": "photo 3 (6)",
			"link": "https://www.flickr.com/photos/139350096@N08/25643081022/",
			"media": {"m":"https://farm2.staticflickr.com/1687/25643081022_25592bbacb_m.jpg"},
			"date_taken": "2014-02-08T13:51:55-08:00",
			"description": " <p><a href=\"https://www.flickr.com/people/139350096@N08/\">myheirloomm<\/a> posted a photo:<\/p> <p><a href=\"https://www.flickr.com/photos/139350096@N08/25643081022/\" title=\"photo 3 (6)\"><img src=\"https://farm2.staticflickr.com/1687/25643081022_25592bbacb_m.jpg\" width=\"180\" height=\"240\" alt=\"photo 3 (6)\" /><\/a><\/p> ",
			"published": "2016-03-13T20:01:01Z",
			"author": "nobody@flickr.com (myheirloomm)",
			"author_id": "139350096@N08",
			"tags": ""
	   },
	   {
			"title": "photo 3 (5)",
			"link": "https://www.flickr.com/photos/139350096@N08/25133595914/",
			"media": {"m":"https://farm2.staticflickr.com/1598/25133595914_1a7144b608_m.jpg"},
			"date_taken": "2014-02-08T13:47:29-08:00",
			"description": " <p><a href=\"https://www.flickr.com/people/139350096@N08/\">myheirloomm<\/a> posted a photo:<\/p> <p><a href=\"https://www.flickr.com/photos/139350096@N08/25133595914/\" title=\"photo 3 (5)\"><img src=\"https://farm2.staticflickr.com/1598/25133595914_1a7144b608_m.jpg\" width=\"180\" height=\"240\" alt=\"photo 3 (5)\" /><\/a><\/p> ",
			"published": "2016-03-13T20:01:00Z",
			"author": "nobody@flickr.com (myheirloomm)",
			"author_id": "139350096@N08",
			"tags": ""
	   },
	   {
			"title": "photo 3 (4)",
			"link": "https://www.flickr.com/photos/139350096@N08/25133594774/",
			"media": {"m":"https://farm2.staticflickr.com/1494/25133594774_60a5b7ca07_m.jpg"},
			"date_taken": "2014-02-08T13:45:42-08:00",
			"description": " <p><a href=\"https://www.flickr.com/people/139350096@N08/\">myheirloomm<\/a> posted a photo:<\/p> <p><a href=\"https://www.flickr.com/photos/139350096@N08/25133594774/\" title=\"photo 3 (4)\"><img src=\"https://farm2.staticflickr.com/1494/25133594774_60a5b7ca07_m.jpg\" width=\"180\" height=\"240\" alt=\"photo 3 (4)\" /><\/a><\/p> ",
			"published": "2016-03-13T20:00:57Z",
			"author": "nobody@flickr.com (myheirloomm)",
			"author_id": "139350096@N08",
			"tags": ""
	   },
	   {
			"title": "photo 3 (3)",
			"link": "https://www.flickr.com/photos/139350096@N08/25133594154/",
			"media": {"m":"https://farm2.staticflickr.com/1700/25133594154_d67efb366d_m.jpg"},
			"date_taken": "2014-02-08T13:40:20-08:00",
			"description": " <p><a href=\"https://www.flickr.com/people/139350096@N08/\">myheirloomm<\/a> posted a photo:<\/p> <p><a href=\"https://www.flickr.com/photos/139350096@N08/25133594154/\" title=\"photo 3 (3)\"><img src=\"https://farm2.staticflickr.com/1700/25133594154_d67efb366d_m.jpg\" width=\"180\" height=\"240\" alt=\"photo 3 (3)\" /><\/a><\/p> ",
			"published": "2016-03-13T20:00:56Z",
			"author": "nobody@flickr.com (myheirloomm)",
			"author_id": "139350096@N08",
			"tags": ""
	   },
	   {
			"title": "photo 3 (2)",
			"link": "https://www.flickr.com/photos/139350096@N08/25137442873/",
			"media": {"m":"https://farm2.staticflickr.com/1563/25137442873_750aae9912_m.jpg"},
			"date_taken": "2014-02-08T13:23:57-08:00",
			"description": " <p><a href=\"https://www.flickr.com/people/139350096@N08/\">myheirloomm<\/a> posted a photo:<\/p> <p><a href=\"https://www.flickr.com/photos/139350096@N08/25137442873/\" title=\"photo 3 (2)\"><img src=\"https://farm2.staticflickr.com/1563/25137442873_750aae9912_m.jpg\" width=\"180\" height=\"240\" alt=\"photo 3 (2)\" /><\/a><\/p> ",
			"published": "2016-03-13T20:00:54Z",
			"author": "nobody@flickr.com (myheirloomm)",
			"author_id": "139350096@N08",
			"tags": ""
	   },
	   {
			"title": "Iris plate",
			"link": "https://www.flickr.com/photos/139350096@N08/25737971906/",
			"media": {"m":"https://farm2.staticflickr.com/1702/25737971906_bff6054278_m.jpg"},
			"date_taken": "2014-02-08T13:22:33-08:00",
			"description": " <p><a href=\"https://www.flickr.com/people/139350096@N08/\">myheirloomm<\/a> posted a photo:<\/p> <p><a href=\"https://www.flickr.com/photos/139350096@N08/25737971906/\" title=\"Iris plate\"><img src=\"https://farm2.staticflickr.com/1702/25737971906_bff6054278_m.jpg\" width=\"240\" height=\"180\" alt=\"Iris plate\" /><\/a><\/p> ",
			"published": "2016-03-13T20:00:52Z",
			"author": "nobody@flickr.com (myheirloomm)",
			"author_id": "139350096@N08",
			"tags": ""
	   },
	   {
			"title": "photo 2",
			"link": "https://www.flickr.com/photos/139350096@N08/25737970906/",
			"media": {"m":"https://farm2.staticflickr.com/1665/25737970906_cfbe424d83_m.jpg"},
			"date_taken": "2014-02-08T13:21:33-08:00",
			"description": " <p><a href=\"https://www.flickr.com/people/139350096@N08/\">myheirloomm<\/a> posted a photo:<\/p> <p><a href=\"https://www.flickr.com/photos/139350096@N08/25737970906/\" title=\"photo 2\"><img src=\"https://farm2.staticflickr.com/1665/25737970906_cfbe424d83_m.jpg\" width=\"180\" height=\"240\" alt=\"photo 2\" /><\/a><\/p> ",
			"published": "2016-03-13T20:00:50Z",
			"author": "nobody@flickr.com (myheirloomm)",
			"author_id": "139350096@N08",
			"tags": ""
	   }
        ]
})